ngsderive/__init__.py
ngsderive/__main__.py
ngsderive/commands/__init__.py
ngsderive/commands/encoding.py
ngsderive/commands/endedness.py
ngsderive/commands/instrument.py
ngsderive/commands/junction_annotation.py
ngsderive/commands/readlen.py
ngsderive/commands/strandedness.py
ngsderive/utils.py
ngsderive-4.0.0.dist-info/LICENSE.md
ngsderive-4.0.0.dist-info/METADATA
ngsderive-4.0.0.dist-info/WHEEL
ngsderive-4.0.0.dist-info/entry_points.txt
ngsderive-4.0.0.dist-info/RECORD
