Metadata-Version: 2.1
Name: ngsderive
Version: 4.0.0
Summary: Forensic analysis tool useful in backwards computing information from next-generation sequencing data.
Home-page: https://github.com/claymcleod/ngsderive
License: MIT
Keywords: bioinformatics,genomics,sam,bam,fastq
Author: Clay McLeod
Author-email: Clay.McLeod@STJUDE.org
Requires-Python: >=3.8,<4.0
Classifier: Development Status :: 4 - Beta
Classifier: License :: OSI Approved :: MIT License
Classifier: Operating System :: OS Independent
Classifier: Programming Language :: Python :: 3
Classifier: Programming Language :: Python :: 3.8
Classifier: Programming Language :: Python :: 3.9
Classifier: Programming Language :: Python :: 3.10
Classifier: Programming Language :: Python :: 3.11
Classifier: Topic :: Scientific/Engineering :: Bio-Informatics
Requires-Dist: colorlog (>=6.6.0,<7.0.0)
Requires-Dist: gtfparse (>=1.2.1,<2.0.0)
Requires-Dist: pygtrie (>=2.5.0,<3.0.0)
Requires-Dist: pysam (>=0.21,<0.22)
Requires-Dist: pytabix (>=0.1,<0.2)
Requires-Dist: rstr (>=3.0.0,<4.0.0)
Requires-Dist: sortedcontainers (>=2.4.0,<3.0.0)
Project-URL: Repository, https://github.com/claymcleod/ngsderive
